tempmail/__init__.py
tempmail/client.py
tempmail/exceptions.py
tempmail/models.py
tempmail/py.typed
temp_mail-1.0.1.dist-info/licenses/LICENSE
temp_mail-1.0.1.dist-info/WHEEL
temp_mail-1.0.1.dist-info/METADATA
temp_mail-1.0.1.dist-info/RECORD
