Metadata-Version: 2.4
Name: temp-mail
Version: 1.0.1
Summary: Official Temp Mail API (https://temp-mail.io) Wrapper for Python.
Keywords: temp-mail,temp-mail-api,tempmail,temp-mail-io
Requires-Python: >=3.8
Classifier: Programming Language :: Python :: 3
Classifier: Programming Language :: Python :: 3.8
Classifier: Programming Language :: Python :: 3.9
Classifier: Programming Language :: Python :: 3.10
Classifier: Programming Language :: Python :: 3.11
Classifier: Programming Language :: Python :: 3.12
Classifier: Programming Language :: Python :: 3.13
Classifier: License :: OSI Approved :: MIT License
Classifier: Operating System :: OS Independent
Classifier: Development Status :: 5 - Production/Stable
Classifier: Intended Audience :: Developers
Classifier: Intended Audience :: End Users/Desktop
License-File: LICENSE
Requires-Dist: httpx>=0.25.0, <1
Requires-Dist: pytest>=6.0.0 ; extra == "dev"
Requires-Dist: pytest-cov>=2.10.0 ; extra == "dev"
Requires-Dist: black>=21.0.0 ; extra == "dev"
Requires-Dist: isort>=5.0.0 ; extra == "dev"
Requires-Dist: mypy>=0.800 ; extra == "dev"
Requires-Dist: setuptools ; extra == "dev"
Project-URL: Source, https://github.com/temp-mail-io/temp-mail-python
Provides-Extra: dev
